invoice_generator/__main__.py
invoice_generator/invoice_creator.py
invoice_generator_bertollo-0.1.0.dist-info/METADATA
invoice_generator_bertollo-0.1.0.dist-info/WHEEL
invoice_generator_bertollo-0.1.0.dist-info/entry_points.txt
invoice_generator_bertollo-0.1.0.dist-info/top_level.txt
invoice_generator_bertollo-0.1.0.dist-info/RECORD
