Metadata-Version: 2.1
Name: invoice_generator_bertollo
Version: 0.1.0
Summary: A package to generate invoices from JSON order data.
Author: Victor Bertollo
Author-email: bertollo.victor@gmail.com
